ctseval/__init__.py
ctseval/_ctseval.c
ctseval/_ctseval.cpython-39-darwin.so
ctseval/create_benchmark_data.py
ctseval/ctseval.c
ctseval/test_utils.py
ctseval/utils.py
ctseval/include/ctseval.h
ctseval-0.1.0.dist-info/LICENSE
ctseval-0.1.0.dist-info/METADATA
ctseval-0.1.0.dist-info/WHEEL
ctseval-0.1.0.dist-info/top_level.txt
ctseval-0.1.0.dist-info/RECORD
