Metadata-Version: 2.1
Name: ctseval
Version: 0.1.0
Summary: A package for evaluating clinical time series predictions
Home-page: https://github.com/michaelgao8/ctseval
Author: Michael Gao
Author-email: Michael Gao <michaelgao8@gmail.com>
License: MIT License
Project-URL: Homepage, https://github.com/michaelgao8/ctseval
Keywords: clinical,time series,evaluation
Classifier: Programming Language :: Python :: 3
Classifier: License :: OSI Approved :: MIT License
Classifier: Operating System :: OS Independent
Requires-Python: >=3.6
License-File: LICENSE
Requires-Dist: numpy
Requires-Dist: pandas
